[
    {"sg": "gbikí", "fr": "la sueur, la transpiration", "en": "sweat, perspiration"},
    {"sg": "mí", "fr": "la chair", "en": "flesh"},
    {"sg": "póró tí teré", "fr": "la peau", "en": "skin"},
    {"sg": "kua", "fr": "le poil", "en": "[body] hair"},
    {"sg": "kúá tí li", "fr": "le cheveu / les cheveux", "en": "hair"},
    {"sg": "biyo tí li", "fr": "le crâne", "en": "skull"},
    {"sg": "li", "fr": "la tête", "en": "head"},
    {"sg": "ndo tí lé", "fr": "le front", "en": "forehead"},
    {"sg": "kpeli", "fr": "le cerveau", "en": "brain"},
    {"sg": "sakpeli", "fr": "la cervelle", "en": "brain"},
    {"sg": "yingɔ", "fr": "l'âme, l'esprit", "en": "soul, spirit"},
    {"sg": "suma, sio", "fr": "le rêve", "en": "dream"},
    {"sg": "sioní bango-li", "fr": "le cauchemar", "en": "nightmare"},
    {"sg": "lé", "fr": "le visage, (la figure)", "en": "face"},
    {"sg": "lé", "fr": "l'œil / les yeux", "en": "eye(s)"},
    {"sg": "ngúlé", "fr": "la larme", "en": "tear, teardrop"},
    {"sg": "mɛ", "fr": "l'oreille", "en": "ear"},
    {"sg": "hɔn", "fr": "le nez", "en": "nose"},
    {"sg": "dú tí hɔn", "fr": "la narine", "en": "nostril"},
    {"sg": "kuayángá", "fr": "la moustache", "en": "mustache"},
    {"sg": "kúá tí yángá", "fr": "la barbe", "en": "beard"},
    {"sg": "ngbángbá", "fr": "la joue", "en": "cheek"},
    {"sg": "bio ngbángbá", "fr": "la mâchoire", "en": "jaw"},
    {"sg": "yángá", "fr": "la bouche", "en": "mouth"},
    {"sg": "poroyángá", "fr": "la lèvre", "en": "lip"},
    {"sg": "ngú tí yángá", "fr": "la salive", "en": "saliva"},
    {"sg": "furusa", "fr": "la bave", "en": "dribble"},
    {"sg": "soro", "fr": "le crachat", "en": "spit"},
    {"sg": "mɛngá", "fr": "la langue", "en": "tongue"},
    {"sg": "pɛmbɛ", "fr": "la dent / les dents", "en": "tooth / teeth"},
    {"sg": "gbe tí yángá", "fr": "le menton", "en": "chin"},
    {"sg": "gó", "fr": "le cou", "en": "neck"},
    {"sg": "gbegó", "fr": "la gorge", "en": "throat"},
    {"sg": "mɛ", "fr": "les seins", "en": "breast"},
    {"sg": "bé", "fr": "le cœur", "en": "heart"},
    {"sg": "sisato", "fr": "l'artère", "en": "artery"},
    {"sg": "sisa", "fr": "la veine", "en": "vein"},
    {"sg": "mɛnɛ", "fr": "le sang", "en": "blood"},
    {"sg": "fúfú", "fr": "le poumon", "en": "lung"},
    {"sg": "túrúmbu", "fr": "le nombril", "en": "navel"},
    {"sg": "yá", "fr": "le ventre", "en": "belly"},
    {"sg": "gbeyá", "fr": "l'abdomen", "en": "belly"},
    {"sg": "kundu", "fr": "l'estomac", "en": "stomach"},
    {"sg": "ngbénebé", "fr": "la rate", "en": "spleen"},
    {"sg": "tí yá", "fr": "l'intestin", "en": "intestine"},
    {"sg": "bɛ", "fr": "le foie", "en": "liver"},
    {"sg": "mísahínon", "fr": "le rein", "en": "kidney"},
    {"sg": "da-hínon", "fr": "la vessie", "en": "bladder"},
    {"sg": "ínɔ", "fr": "l'urine", "en": null},
    {"sg": "mísa", "fr": "l'organe", "en": "organ"},
    {"sg": "sisa", "fr": "le nerf", "en": "nerve"},
    {"sg": "mí", "fr": "le muscle", "en": null},
    {"sg": "gbábio", "fr": "le squelette", "en": "skeleton"},
    {"sg": "bíó", "fr": "l'os / les os", "en": "bone(s)"},
    {"sg": "bíókate", "fr": "la côte", "en": "rib"},
    {"sg": "kate", "fr": "la poitrine, le torse", "en": "chest"},
    {"sg": "pɛkɔ", "fr": "le dos", "en": "back"},
    {"sg": "fúnda-yá", "fr": "la hanche", "en": "hip"},
    {"sg": "yá", "fr": "la taille", "en": "waist"},
    {"sg": "pámboti", "fr": "l'épaule", "en": "shoulder"},
    {"sg": "mabɔkɔ", "fr": "le bras", "en": "arm"},
    {"sg": "gbeti", "fr": "l'aisselle", "en": "armpit"},
    {"sg": "ngoti", "fr": "le coude", "en": "elbow"},
    {"sg": "hónti", "fr": "le poignet", "en": "wrist"},
    {"sg": "gobo", "fr": "le poing", "en": "fist"},
    {"sg": "yambati", "fr": "la paume de la main", "en": "palm of the hand"},
    {"sg": "mabɔkɔ", "fr": "la main", "en": "hand"},
    {"sg": "kota limabɔkɔ", "fr": "le pouce", "en": "thumb"},
    {"sg": "kété/nzína mabɔkɔ", "fr": "le doigt", "en": "finger"},
    {"sg": "nzene tí mabɔkɔ", "fr": "l'ongle", "en": "fingernail, nail"},
    {"sg": "kenge na dondo", "fr": "le sexe", "en": "sex"},
    {"sg": "kéngé", "fr": "le pénis, (la verge)", "en": "penis"},
    {"sg": "ngúteré-kɔli", "fr": "le sperme", "en": "sperm"},
    {"sg": "dondo", "fr": "le vagin", "en": "vagina"},
    {"sg": "lendá", "fr": "le clitoris", "en": null},
    {"sg": "dú tí ngbondá", "fr": "l'anus", "en": null},
    {"sg": "ngbondá", "fr": "le derrière, les fesses", "en": "bottom, buttocks"},
    {"sg": "kuni", "fr": "la cuisse", "en": "thigh"},
    {"sg": "gɛrɛ", "fr": "la jambe", "en": "leg"},
    {"sg": "likuni", "fr": "le genou", "en": "knee"},
    {"sg": "likuni", "fr": "la rotule", "en": "kneecap, (patella)"},
    {"sg": "gbánganga", "fr": "le mollet", "en": "calf"},
    {"sg": "kútugeré", "fr": "la cheville", "en": "ankle"},
    {"sg": "ndá-gɛrɛ", "fr": "le talon", "en": "heel"},
    {"sg": "gbe-gɛrɛ", "fr": "la plante du pied", "en": "sole of the foot"},
    {"sg": "gɛrɛ", "fr": "le pied / les pieds", "en": "foot / feet"},
    {"sg": "kété/nzína gɛrɛ", "fr": "le doigt de pied, l'orteil", "en": "toe"},
    {"sg": "séní", "fr": "la santé", "en": "health"},
    {"sg": "kobéla", "fr": "la maladie", "en": "disease"},
    {"sg": "zo tí kobéla", "fr": "le malade", "en": "ill/sick person"},
    {"sg": "ambilási", "fr": "l'ambulance", "en": null},
    {"sg": "wa-ambilási", "fr": "l'ambulancier", "en": null},
    {"sg": "danganga", "fr": "l'hôpital, la clinique", "en": "hospital, clinic"},
    {"sg": "kété wanganga", "fr": "l'infirmière", "en": "nurse"},
    {"sg": "dokotoro, wanganga", "fr": "le docteur, le médecin", "en": "doctor, physician"},
    {"sg": "wanganga-pembe", "fr": "le dentiste", "en": "dentist"},
    {"sg": "wasurungo", "fr": "le chirurgien", "en": "surgeon"},
    {"sg": "dakango-yoró", "fr": "la pharmacie", "en": "pharmacy, drugstore"},
    {"sg": "wakango-yoró", "fr": "le pharmacien", "en": "pharmacist"},
    {"sg": "yoró", "fr": "le médicament", "en": "medication"},
    {"sg": "poro, kondóme", "fr": "le préservatif, la \"capote\"", "en": "condom"},
    {"sg": "siongahozo", "fr": "le SIDA", "en": "AIDS"},
    {"sg": "wasiongahozo", "fr": "le sidéen", "en": "person with AIDS"},
    {"sg": "kúá", "fr": "le cadavre", "en": "cadaver, corpse"}
]
